nasaapi/__init__.py
python_nasa_api-0.0.2.dist-info/METADATA
python_nasa_api-0.0.2.dist-info/WHEEL
python_nasa_api-0.0.2.dist-info/top_level.txt
python_nasa_api-0.0.2.dist-info/RECORD
