Metadata-Version: 2.1
Name: python-nasa-api
Version: 0.0.2
Summary: Simple NASA Api Wrapper written in Python!
Home-page: UNKNOWN
License: MIT
Keywords: python-nasa-api
Platform: UNKNOWN
Classifier: License :: OSI Approved :: MIT License
Classifier: Programming Language :: Python :: 3
Classifier: Programming Language :: Python :: 3.7
